streamlit_timeago/__init__.py
streamlit_timeago/example.py
streamlit_timeago/frontend/build/asset-manifest.json
streamlit_timeago/frontend/build/index.html
streamlit_timeago/frontend/build/static/js/main.7d190ba8.js
streamlit_timeago/frontend/build/static/js/main.7d190ba8.js.LICENSE.txt
streamlit_timeago-0.1.2.dist-info/LICENSE
streamlit_timeago-0.1.2.dist-info/METADATA
streamlit_timeago-0.1.2.dist-info/WHEEL
streamlit_timeago-0.1.2.dist-info/top_level.txt
streamlit_timeago-0.1.2.dist-info/RECORD
