Metadata-Version: 2.1
Name: streamlit-timeago
Version: 0.1.2
Summary: Streamlit wrapper of timeago-react to render time ago
Home-page: https://github.com/prihoda/streamlit-timeago
Author: David Prihoda
Author-email: david.prihoda@gmail.com
Requires-Python: >=3.7
License-File: LICENSE
Requires-Dist: streamlit >=0.63
Provides-Extra: devel
Requires-Dist: wheel ; extra == 'devel'
Requires-Dist: pytest ==7.4.0 ; extra == 'devel'
Requires-Dist: playwright ==1.48.0 ; extra == 'devel'
Requires-Dist: requests ==2.31.0 ; extra == 'devel'
Requires-Dist: pytest-playwright-snapshot ==1.0 ; extra == 'devel'
Requires-Dist: pytest-rerunfailures ==12.0 ; extra == 'devel'
